LICENSE
bodhiext/openai/__init__.py
bodhiext/openai/_openai.py
bodhiext/openai/_version.py
bodhiext_openai-0.1.2.dist-info/LICENSE
bodhiext_openai-0.1.2.dist-info/METADATA
bodhiext_openai-0.1.2.dist-info/WHEEL
bodhiext_openai-0.1.2.dist-info/entry_points.txt
bodhiext_openai-0.1.2.dist-info/RECORD
