Metadata-Version: 2.1
Name: bodhiext.openai
Version: 0.1.2
Summary: Bodhilib plugin for OpenAI APIs
License: MIT
Requires-Python: >=3.8.1,<3.12
Classifier: License :: OSI Approved :: MIT License
Classifier: Programming Language :: Python :: 3
Classifier: Programming Language :: Python :: 3.9
Classifier: Programming Language :: Python :: 3.10
Classifier: Programming Language :: Python :: 3.11
Requires-Dist: bodhilib (>=0.1.0,<0.2.0)
Requires-Dist: openai (>=0.28.1,<0.29.0)
Requires-Dist: pydantic (>=1,<2)
